lomltk/__init__.py
lomltk/cli.py
lomltk/image_processing.py
lomltk/json.py
lomltk/logging.py
lomltk/multiprocessing.py
lomltk/path.py
lomltk/random.py
lomltk/string.py
lomltk/typing.py
lomltk/utils.py
lomltk/pandas/__init__.py
lomltk/pandas/utils.py
lomltk/torch/__init__.py
lomltk/torch/distributed.py
lomltk/torch/models.py
lomltk/torch/utils.py
lomltk-0.0.1.dist-info/LICENSE
lomltk-0.0.1.dist-info/METADATA
lomltk-0.0.1.dist-info/WHEEL
lomltk-0.0.1.dist-info/top_level.txt
lomltk-0.0.1.dist-info/RECORD
