Metadata-Version: 2.1
Name: lomltk
Version: 0.0.1
Summary: The lord of Machine Learning toolkits
Home-page: https://github.com/zijian-hu/lomltk
Author: Zijian Hu
Author-email: zijian-hu@outlook.com
Classifier: Programming Language :: Python :: 3
Classifier: License :: OSI Approved :: MIT License
Classifier: Operating System :: OS Independent
Requires-Python: >=3.7
License-File: LICENSE
Requires-Dist: typing-extensions
Requires-Dist: numpy
Requires-Dist: scipy
Requires-Dist: pandas
Requires-Dist: tqdm
Requires-Dist: pillow
Requires-Dist: future
Requires-Dist: joblib
Requires-Dist: requests
Requires-Dist: torch (>=1.0.0)
Requires-Dist: torchvision
Requires-Dist: opencv-contrib-python-headless
